idun_tools/__init__.py
idun_tools/logging.py
idun_tools-0.1.1.dist-info/METADATA
idun_tools-0.1.1.dist-info/WHEEL
idun_tools-0.1.1.dist-info/RECORD
