Metadata-Version: 2.1
Name: idun_tools
Version: 0.1.1
Summary: 
Author: Konstantinos Samaras-Tsakiris
Author-email: konstantinos@iduntechnologies.com
Requires-Python: >=3.10,<4.0
Classifier: Programming Language :: Python :: 3
Classifier: Programming Language :: Python :: 3.10
Classifier: Programming Language :: Python :: 3.11
Requires-Dist: loguru (>=0.7.2,<0.8.0)
